python_base_package/__init__.py
python_base_package/calculator.py
python_base_package-0.1.0.dist-info/LICENSE.txt
python_base_package-0.1.0.dist-info/METADATA
python_base_package-0.1.0.dist-info/WHEEL
python_base_package-0.1.0.dist-info/top_level.txt
python_base_package-0.1.0.dist-info/RECORD
