Metadata-Version: 2.1
Name: python-base-package
Version: 0.1.0
Summary: Python base package
Author: Wojciech Peisert
Author-email: wojtekp@sauron.pl
License: LICENCE.txt
License-File: LICENSE.txt
